cstgs-0.1.7.dist-info/METADATA
cstgs-0.1.7.dist-info/WHEEL
cstgs/__init__.py
cstgs/cstgs.abi3.so
cstgs-0.1.7.dist-info/RECORD
