Metadata-Version: 2.4
Name: cstgs
Version: 0.1.7
Summary: Counting and Sampling Triangles from a Graph Stream, with Python bindings
Author: Amir Hossein Pakdaman
Requires-Python: >=3.9, <4.0
